{
    "summary": {
        "total_pdfs": 24,
        "soft_copy_count": 19,
        "scanned_count": 5,
        "not_found_count": 0,
        "soft_copy_percentage": 79.16666666666666,
        "scanned_percentage": 20.833333333333336
    },
    "documents": {
        "13th_Sangunian/ord2019-080.pdf": {
            "file_path": "/home/dfaurellano/avila/Adal_Smart_Naga_Hackathon/data/ord2019-080.pdf",
            "file_name": "ord2019-080.pdf",
            "exists": true,
            "needs_ocr": false,
            "is_soft_copy": true,
            "is_scanned": false,
            "num_pages": 1,
            "file_size": "194.53 KB",
            "folder": "13th_Sangunian",
            "url": "https://drive.google.com/file/d/1GglNkVBf4LUlRUJVVjPmzf5i9LZESFXl/view?usp=drivesdk",
            "file_id": "1GglNkVBf4LUlRUJVVjPmzf5i9LZESFXl",
            "direct_download": "https://drive.google.com/uc?id=1GglNkVBf4LUlRUJVVjPmzf5i9LZESFXl&export=download",
            "processing_type": "standard_extraction"
        },
        "13th_Sangunian/ord2019-082.pdf": {
            "file_path": "/home/dfaurellano/avila/Adal_Smart_Naga_Hackathon/data/ord2019-082.pdf",
            "file_name": "ord2019-082.pdf",
            "exists": true,
            "needs_ocr": false,
            "is_soft_copy": true,
            "is_scanned": false,
            "num_pages": 1,
            "file_size": "201.13 KB",
            "folder": "13th_Sangunian",
            "url": "https://drive.google.com/file/d/1mbiRgOWSjwUPOUc1bm4sigVX6s_SSQGW/view?usp=drivesdk",
            "file_id": "1mbiRgOWSjwUPOUc1bm4sigVX6s_SSQGW",
            "direct_download": "https://drive.google.com/uc?id=1mbiRgOWSjwUPOUc1bm4sigVX6s_SSQGW&export=download",
            "processing_type": "standard_extraction"
        },
        "13th_Sangunian/ord2019-072.pdf": {
            "file_path": "/home/dfaurellano/avila/Adal_Smart_Naga_Hackathon/data/ord2019-072.pdf",
            "file_name": "ord2019-072.pdf",
            "exists": true,
            "needs_ocr": false,
            "is_soft_copy": true,
            "is_scanned": false,
            "num_pages": 1,
            "file_size": "145.58 KB",
            "folder": "13th_Sangunian",
            "url": "https://drive.google.com/file/d/1TA0CxF0xCGS7mBG8ww4MAkkonYCzBzCM/view?usp=drivesdk",
            "file_id": "1TA0CxF0xCGS7mBG8ww4MAkkonYCzBzCM",
            "direct_download": "https://drive.google.com/uc?id=1TA0CxF0xCGS7mBG8ww4MAkkonYCzBzCM&export=download",
            "processing_type": "standard_extraction"
        },
        "13th_Sangunian/ord2019-106.pdf": {
            "file_path": "/home/dfaurellano/avila/Adal_Smart_Naga_Hackathon/data/ord2019-106.pdf",
            "file_name": "ord2019-106.pdf",
            "exists": true,
            "needs_ocr": false,
            "is_soft_copy": true,
            "is_scanned": false,
            "num_pages": 1,
            "file_size": "198.19 KB",
            "folder": "13th_Sangunian",
            "url": "https://drive.google.com/file/d/152kiF896FB6orRe8nTgY7YWyPdoHheov/view?usp=drivesdk",
            "file_id": "152kiF896FB6orRe8nTgY7YWyPdoHheov",
            "direct_download": "https://drive.google.com/uc?id=152kiF896FB6orRe8nTgY7YWyPdoHheov&export=download",
            "processing_type": "standard_extraction"
        },
        "13th_Sangunian/ord2019-045.pdf": {
            "file_path": "/home/dfaurellano/avila/Adal_Smart_Naga_Hackathon/data/ord2019-045.pdf",
            "file_name": "ord2019-045.pdf",
            "exists": true,
            "needs_ocr": false,
            "is_soft_copy": true,
            "is_scanned": false,
            "num_pages": 1,
            "file_size": "283.06 KB",
            "folder": "13th_Sangunian",
            "url": "https://drive.google.com/file/d/1UiQulpRrvV__272ADXD50rW1B-IRcqwi/view?usp=drivesdk",
            "file_id": "1UiQulpRrvV__272ADXD50rW1B-IRcqwi",
            "direct_download": "https://drive.google.com/uc?id=1UiQulpRrvV__272ADXD50rW1B-IRcqwi&export=download",
            "processing_type": "standard_extraction"
        },
        "13th_Sangunian/ord2019-062.pdf": {
            "file_path": "/home/dfaurellano/avila/Adal_Smart_Naga_Hackathon/data/ord2019-062.pdf",
            "file_name": "ord2019-062.pdf",
            "exists": true,
            "needs_ocr": false,
            "is_soft_copy": true,
            "is_scanned": false,
            "num_pages": 1,
            "file_size": "265.37 KB",
            "folder": "13th_Sangunian",
            "url": "https://drive.google.com/file/d/1unlKQQQ0EZaZ82SMqi2wXQzbpvqYKvKg/view?usp=drivesdk",
            "file_id": "1unlKQQQ0EZaZ82SMqi2wXQzbpvqYKvKg",
            "direct_download": "https://drive.google.com/uc?id=1unlKQQQ0EZaZ82SMqi2wXQzbpvqYKvKg&export=download",
            "processing_type": "standard_extraction"
        },
        "13th_Sangunian/ord2019-046.pdf": {
            "file_path": "/home/dfaurellano/avila/Adal_Smart_Naga_Hackathon/data/ord2019-046.pdf",
            "file_name": "ord2019-046.pdf",
            "exists": true,
            "needs_ocr": false,
            "is_soft_copy": true,
            "is_scanned": false,
            "num_pages": 1,
            "file_size": "259.05 KB",
            "folder": "13th_Sangunian",
            "url": "https://drive.google.com/file/d/1al-XEZ8QvP4w4bG0jzyJAHCSv-JHarDp/view?usp=drivesdk",
            "file_id": "1al-XEZ8QvP4w4bG0jzyJAHCSv-JHarDp",
            "direct_download": "https://drive.google.com/uc?id=1al-XEZ8QvP4w4bG0jzyJAHCSv-JHarDp&export=download",
            "processing_type": "standard_extraction"
        },
        "13th_Sangunian/ord2022-022.pdf": {
            "file_path": "/home/dfaurellano/avila/Adal_Smart_Naga_Hackathon/data/ord2022-022.pdf",
            "file_name": "ord2022-022.pdf",
            "exists": true,
            "needs_ocr": true,
            "is_soft_copy": false,
            "is_scanned": true,
            "num_pages": 1,
            "file_size": "264.22 KB",
            "folder": "13th_Sangunian",
            "url": "https://drive.google.com/file/d/1BWJOr5LHdskiHG3mVR3cOqh_ze6z-8XK/view?usp=drivesdk",
            "file_id": "1BWJOr5LHdskiHG3mVR3cOqh_ze6z-8XK",
            "direct_download": "https://drive.google.com/uc?id=1BWJOr5LHdskiHG3mVR3cOqh_ze6z-8XK&export=download",
            "processing_type": "ocr_required"
        },
        "14th_Samgunian/ord2023-010.pdf": {
            "file_path": "/home/dfaurellano/avila/Adal_Smart_Naga_Hackathon/data/ord2023-010.pdf",
            "file_name": "ord2023-010.pdf",
            "exists": true,
            "needs_ocr": true,
            "is_soft_copy": false,
            "is_scanned": true,
            "num_pages": 7,
            "file_size": "2.11 MB",
            "folder": "14th_Samgunian",
            "url": "https://drive.google.com/file/d/1n2PX0y5ntVOGsiwYLgh-ellikzymeygy/view?usp=drivesdk",
            "file_id": "1n2PX0y5ntVOGsiwYLgh-ellikzymeygy",
            "direct_download": "https://drive.google.com/uc?id=1n2PX0y5ntVOGsiwYLgh-ellikzymeygy&export=download",
            "processing_type": "ocr_required"
        },
        "14th_Samgunian/ord2023-004.pdf": {
            "file_path": "/home/dfaurellano/avila/Adal_Smart_Naga_Hackathon/data/ord2023-004.pdf",
            "file_name": "ord2023-004.pdf",
            "exists": true,
            "needs_ocr": true,
            "is_soft_copy": false,
            "is_scanned": true,
            "num_pages": 5,
            "file_size": "1.91 MB",
            "folder": "14th_Samgunian",
            "url": "https://drive.google.com/file/d/1IKg9UCytCPcupgAZ69gHHCamYyhd-4Ov/view?usp=drivesdk",
            "file_id": "1IKg9UCytCPcupgAZ69gHHCamYyhd-4Ov",
            "direct_download": "https://drive.google.com/uc?id=1IKg9UCytCPcupgAZ69gHHCamYyhd-4Ov&export=download",
            "processing_type": "ocr_required"
        },
        "14th_Samgunian/ord2023-006.pdf": {
            "file_path": "/home/dfaurellano/avila/Adal_Smart_Naga_Hackathon/data/ord2023-006.pdf",
            "file_name": "ord2023-006.pdf",
            "exists": true,
            "needs_ocr": true,
            "is_soft_copy": false,
            "is_scanned": true,
            "num_pages": 4,
            "file_size": "1.54 MB",
            "folder": "14th_Samgunian",
            "url": "https://drive.google.com/file/d/1GMsARa5xHvy089xgZft0FBGr68T8HKjC/view?usp=drivesdk",
            "file_id": "1GMsARa5xHvy089xgZft0FBGr68T8HKjC",
            "direct_download": "https://drive.google.com/uc?id=1GMsARa5xHvy089xgZft0FBGr68T8HKjC&export=download",
            "processing_type": "ocr_required"
        },
        "14th_Samgunian/ord2023-009.pdf": {
            "file_path": "/home/dfaurellano/avila/Adal_Smart_Naga_Hackathon/data/ord2023-009.pdf",
            "file_name": "ord2023-009.pdf",
            "exists": true,
            "needs_ocr": false,
            "is_soft_copy": true,
            "is_scanned": false,
            "num_pages": 4,
            "file_size": "1.11 MB",
            "folder": "14th_Samgunian",
            "url": "https://drive.google.com/file/d/1UHrAhmVEOly7HlD6TqTdwYY2NV-8uML-/view?usp=drivesdk",
            "file_id": "1UHrAhmVEOly7HlD6TqTdwYY2NV-8uML-",
            "direct_download": "https://drive.google.com/uc?id=1UHrAhmVEOly7HlD6TqTdwYY2NV-8uML-&export=download",
            "processing_type": "standard_extraction"
        },
        "14th_Samgunian/ord2023-002.pdf": {
            "file_path": "/home/dfaurellano/avila/Adal_Smart_Naga_Hackathon/data/ord2023-002.pdf",
            "file_name": "ord2023-002.pdf",
            "exists": true,
            "needs_ocr": true,
            "is_soft_copy": false,
            "is_scanned": true,
            "num_pages": 1,
            "file_size": "344.10 KB",
            "folder": "14th_Samgunian",
            "url": "https://drive.google.com/file/d/1Hu-bpt0Zf3Cv3ybncXuxCVxpRY-rAmPP/view?usp=drivesdk",
            "file_id": "1Hu-bpt0Zf3Cv3ybncXuxCVxpRY-rAmPP",
            "direct_download": "https://drive.google.com/uc?id=1Hu-bpt0Zf3Cv3ybncXuxCVxpRY-rAmPP&export=download",
            "processing_type": "ocr_required"
        },
        "14th_Samgunian/Ordno-2025-047-Renaming-Liboton-Street-to-J.-Antonio-Carpio-Street-1.pdf": {
            "file_path": "/home/dfaurellano/avila/Adal_Smart_Naga_Hackathon/data/Ordno-2025-047-Renaming-Liboton-Street-to-J.-Antonio-Carpio-Street-1.pdf",
            "file_name": "Ordno-2025-047-Renaming-Liboton-Street-to-J.-Antonio-Carpio-Street-1.pdf",
            "exists": true,
            "needs_ocr": false,
            "is_soft_copy": true,
            "is_scanned": false,
            "num_pages": 3,
            "file_size": "342.36 KB",
            "folder": "14th_Samgunian",
            "url": "https://drive.google.com/file/d/1dwdrlfWy2xw5X_HQvS5TRAUg3DyfbVI1/view?usp=drivesdk",
            "file_id": "1dwdrlfWy2xw5X_HQvS5TRAUg3DyfbVI1",
            "direct_download": "https://drive.google.com/uc?id=1dwdrlfWy2xw5X_HQvS5TRAUg3DyfbVI1&export=download",
            "processing_type": "standard_extraction"
        },
        "14th_Samgunian/Ordno-2025-048-Underground-Cabling-Plus.pdf": {
            "file_path": "/home/dfaurellano/avila/Adal_Smart_Naga_Hackathon/data/Ordno-2025-048-Underground-Cabling-Plus.pdf",
            "file_name": "Ordno-2025-048-Underground-Cabling-Plus.pdf",
            "exists": true,
            "needs_ocr": false,
            "is_soft_copy": true,
            "is_scanned": false,
            "num_pages": 5,
            "file_size": "1.37 MB",
            "folder": "14th_Samgunian",
            "url": "https://drive.google.com/file/d/1dIsFUZyvOGjysvrbjCkcU16B7GEn56wd/view?usp=drivesdk",
            "file_id": "1dIsFUZyvOGjysvrbjCkcU16B7GEn56wd",
            "direct_download": "https://drive.google.com/uc?id=1dIsFUZyvOGjysvrbjCkcU16B7GEn56wd&export=download",
            "processing_type": "standard_extraction"
        },
        "14th_Samgunian/Ordno-2025-051-SGLGB-Incentives-Fund.pdf": {
            "file_path": "/home/dfaurellano/avila/Adal_Smart_Naga_Hackathon/data/Ordno-2025-051-SGLGB-Incentives-Fund.pdf",
            "file_name": "Ordno-2025-051-SGLGB-Incentives-Fund.pdf",
            "exists": true,
            "needs_ocr": false,
            "is_soft_copy": true,
            "is_scanned": false,
            "num_pages": 2,
            "file_size": "508.40 KB",
            "folder": "14th_Samgunian",
            "url": "https://drive.google.com/file/d/17jmKX7ZNr72Nit3fG2i6RynmVXYF5hll/view?usp=drivesdk",
            "file_id": "17jmKX7ZNr72Nit3fG2i6RynmVXYF5hll",
            "direct_download": "https://drive.google.com/uc?id=17jmKX7ZNr72Nit3fG2i6RynmVXYF5hll&export=download",
            "processing_type": "standard_extraction"
        },
        "15th_Sangunian/Ordno-2025-056-Unified-Route-for-VISTODA-and-LAVISTODA.pdf": {
            "file_path": "/home/dfaurellano/avila/Adal_Smart_Naga_Hackathon/data/Ordno-2025-056-Unified-Route-for-VISTODA-and-LAVISTODA.pdf",
            "file_name": "Ordno-2025-056-Unified-Route-for-VISTODA-and-LAVISTODA.pdf",
            "exists": true,
            "needs_ocr": false,
            "is_soft_copy": true,
            "is_scanned": false,
            "num_pages": 2,
            "file_size": "523.55 KB",
            "folder": "15th_Sangunian",
            "url": "https://drive.google.com/file/d/101bH8VI3A3-8Z9OzhKBpZBi2GspiWKb6/view?usp=drivesdk",
            "file_id": "101bH8VI3A3-8Z9OzhKBpZBi2GspiWKb6",
            "direct_download": "https://drive.google.com/uc?id=101bH8VI3A3-8Z9OzhKBpZBi2GspiWKb6&export=download",
            "processing_type": "standard_extraction"
        },
        "15th_Sangunian/Ordno-2025-053-ePWD-validity-for-5-Years.pdf": {
            "file_path": "/home/dfaurellano/avila/Adal_Smart_Naga_Hackathon/data/Ordno-2025-053-ePWD-validity-for-5-Years.pdf",
            "file_name": "Ordno-2025-053-ePWD-validity-for-5-Years.pdf",
            "exists": true,
            "needs_ocr": false,
            "is_soft_copy": true,
            "is_scanned": false,
            "num_pages": 2,
            "file_size": "670.37 KB",
            "folder": "15th_Sangunian",
            "url": "https://drive.google.com/file/d/1DcZYjO8Q4ZWpkV2gcVHUYhBoo3oOhtfG/view?usp=drivesdk",
            "file_id": "1DcZYjO8Q4ZWpkV2gcVHUYhBoo3oOhtfG",
            "direct_download": "https://drive.google.com/uc?id=1DcZYjO8Q4ZWpkV2gcVHUYhBoo3oOhtfG&export=download",
            "processing_type": "standard_extraction"
        },
        "15th_Sangunian/Ordno-2025-054-Near-Centenarian-Incentive-Ordinance_Senior-Citizens-1.pdf": {
            "file_path": "/home/dfaurellano/avila/Adal_Smart_Naga_Hackathon/data/Ordno-2025-054-Near-Centenarian-Incentive-Ordinance_Senior-Citizens-1.pdf",
            "file_name": "Ordno-2025-054-Near-Centenarian-Incentive-Ordinance_Senior-Citizens-1.pdf",
            "exists": true,
            "needs_ocr": false,
            "is_soft_copy": true,
            "is_scanned": false,
            "num_pages": 2,
            "file_size": "855.26 KB",
            "folder": "15th_Sangunian",
            "url": "https://drive.google.com/file/d/1ZyZQQQRimcbyoJp7pqhSc8x5WRBh-syD/view?usp=drivesdk",
            "file_id": "1ZyZQQQRimcbyoJp7pqhSc8x5WRBh-syD",
            "direct_download": "https://drive.google.com/uc?id=1ZyZQQQRimcbyoJp7pqhSc8x5WRBh-syD&export=download",
            "processing_type": "standard_extraction"
        },
        "15th_Sangunian/Ordno-2025-061-Bantay-Proyekto-Ordinance.pdf": {
            "file_path": "/home/dfaurellano/avila/Adal_Smart_Naga_Hackathon/data/Ordno-2025-061-Bantay-Proyekto-Ordinance.pdf",
            "file_name": "Ordno-2025-061-Bantay-Proyekto-Ordinance.pdf",
            "exists": true,
            "needs_ocr": false,
            "is_soft_copy": true,
            "is_scanned": false,
            "num_pages": 6,
            "file_size": "2.00 MB",
            "folder": "15th_Sangunian",
            "url": "https://drive.google.com/file/d/11Rdw4QHn_UFVt69HTyhCiSG3QlcwnOXc/view?usp=drivesdk",
            "file_id": "11Rdw4QHn_UFVt69HTyhCiSG3QlcwnOXc",
            "direct_download": "https://drive.google.com/uc?id=11Rdw4QHn_UFVt69HTyhCiSG3QlcwnOXc&export=download",
            "processing_type": "standard_extraction"
        },
        "15th_Sangunian/Ordno-2025-060-Disposal-of-Excess-Soil-and-Concrete-Debris-from-Public-Infrastructure-Projects.pdf": {
            "file_path": "/home/dfaurellano/avila/Adal_Smart_Naga_Hackathon/data/Ordno-2025-060-Disposal-of-Excess-Soil-and-Concrete-Debris-from-Public-Infrastructure-Projects.pdf",
            "file_name": "Ordno-2025-060-Disposal-of-Excess-Soil-and-Concrete-Debris-from-Public-Infrastructure-Projects.pdf",
            "exists": true,
            "needs_ocr": false,
            "is_soft_copy": true,
            "is_scanned": false,
            "num_pages": 6,
            "file_size": "1.85 MB",
            "folder": "15th_Sangunian",
            "url": "https://drive.google.com/file/d/1L3TI_GP1SxswAJwO9rpLkMwC_ZwVkNMS/view?usp=drivesdk",
            "file_id": "1L3TI_GP1SxswAJwO9rpLkMwC_ZwVkNMS",
            "direct_download": "https://drive.google.com/uc?id=1L3TI_GP1SxswAJwO9rpLkMwC_ZwVkNMS&export=download",
            "processing_type": "standard_extraction"
        },
        "15th_Sangunian/Ordno-2025-069-Balik-Eskwela-Program.pdf": {
            "file_path": "/home/dfaurellano/avila/Adal_Smart_Naga_Hackathon/data/Ordno-2025-069-Balik-Eskwela-Program.pdf",
            "file_name": "Ordno-2025-069-Balik-Eskwela-Program.pdf",
            "exists": true,
            "needs_ocr": false,
            "is_soft_copy": true,
            "is_scanned": false,
            "num_pages": 10,
            "file_size": "3.17 MB",
            "folder": "15th_Sangunian",
            "url": "https://drive.google.com/file/d/1UGpdX6hyjaQP2rQ1DbfeWsRr24BkqpaQ/view?usp=drivesdk",
            "file_id": "1UGpdX6hyjaQP2rQ1DbfeWsRr24BkqpaQ",
            "direct_download": "https://drive.google.com/uc?id=1UGpdX6hyjaQP2rQ1DbfeWsRr24BkqpaQ&export=download",
            "processing_type": "standard_extraction"
        },
        "15th_Sangunian/Ordno-2025-070-Institutionalizing-the-Approved-LPTRP.pdf": {
            "file_path": "/home/dfaurellano/avila/Adal_Smart_Naga_Hackathon/data/Ordno-2025-070-Institutionalizing-the-Approved-LPTRP.pdf",
            "file_name": "Ordno-2025-070-Institutionalizing-the-Approved-LPTRP.pdf",
            "exists": true,
            "needs_ocr": false,
            "is_soft_copy": true,
            "is_scanned": false,
            "num_pages": 5,
            "file_size": "1.12 MB",
            "folder": "15th_Sangunian",
            "url": "https://drive.google.com/file/d/1m8DOeY8lEHDDw1jPi76hcLa1FahoTG7v/view?usp=drivesdk",
            "file_id": "1m8DOeY8lEHDDw1jPi76hcLa1FahoTG7v",
            "direct_download": "https://drive.google.com/uc?id=1m8DOeY8lEHDDw1jPi76hcLa1FahoTG7v&export=download",
            "processing_type": "standard_extraction"
        },
        "15th_Sangunian/Ordno-2025-067-Consolidated-VISTODA-and-LAVISTODA-Special-trimobile-Franchise-plying-Salunguigui-Cararayan.pdf": {
            "file_path": "/home/dfaurellano/avila/Adal_Smart_Naga_Hackathon/data/Ordno-2025-067-Consolidated-VISTODA-and-LAVISTODA-Special-trimobile-Franchise-plying-Salunguigui-Cararayan.pdf",
            "file_name": "Ordno-2025-067-Consolidated-VISTODA-and-LAVISTODA-Special-trimobile-Franchise-plying-Salunguigui-Cararayan.pdf",
            "exists": true,
            "needs_ocr": false,
            "is_soft_copy": true,
            "is_scanned": false,
            "num_pages": 2,
            "file_size": "466.99 KB",
            "folder": "15th_Sangunian",
            "url": "https://drive.google.com/file/d/1RrcqYEBBYdsfiHCsCVNCYuGZ6MJC5rLp/view?usp=drivesdk",
            "file_id": "1RrcqYEBBYdsfiHCsCVNCYuGZ6MJC5rLp",
            "direct_download": "https://drive.google.com/uc?id=1RrcqYEBBYdsfiHCsCVNCYuGZ6MJC5rLp&export=download",
            "processing_type": "standard_extraction"
        }
    }
}